setup.py
DISAoner_test_12312321.egg-info/PKG-INFO
DISAoner_test_12312321.egg-info/SOURCES.txt
DISAoner_test_12312321.egg-info/dependency_links.txt
DISAoner_test_12312321.egg-info/top_level.txt
my_project/main.py