Metadata-Version: 2.1
Name: DISAoner-test-12312321
Version: 0.1
Summary: Python Distribution Utilities
Author: DISAoner
Author-email: gladun01@gmail.com
